{
  "session_id": "7130212c-9696-43be-8d17-c351d08303cd",
  "username": "Recruiter",
  "session_start_time": "2025-03-20T10:17:13.749645",
  "selected_file": "DataAnalyticsAIMLJD (1).txt",
  "original_jd": "Job Description-\n\nThis role will blend business acumen with technical proficiency, requiring the ability to understand complex business processes and translate them into effective system configurations. You will be a key player in ensuring our systems accurately reflect business needs and operate efficiently. This position will focus heavily on the developing new processes with technical solutions with the vehicle configuration space. The position will utilize ML and AI to quickly develop solutions.\n\n \u2022 Collaborate with stakeholders across various departments to understand business needs, gather detailed requirements, and document them clearly and concisely using various techniques (e.g., user stories, use cases, process flows). \n\n\u2022 Translate business requirements into technical configurations within our [mention specific system] backend. This includes, but is not limited to:\n\n \u2022 Developing and maintaining configuration specifications.\n\n \u2022 Creating and modifying data mappings and integrations.\n\n \u2022 Implementing and testing new configurations.\n\n \u2022 Troubleshooting and resolving configuration-related issues. \n\n\u2022 Analyze existing data to identify trends, inefficiencies, and areas for improvement. This may involve querying databases, generating reports, and visualizing data using appropriate tools. \n\n\u2022 Identify opportunities to streamline business processes and improve system efficiency through configuration changes and best practices. \n\n\u2022 Thoroughly test configurations to ensure they meet requirements and function as expected. Participate in user acceptance testing (UAT). \n\n\u2022 Maintain comprehensive documentation of system configurations, processes, and troubleshooting steps. \n\n\u2022 Work closely with developers, IT support, and other stakeholders to ensure smooth implementation and ongoing support of system configurations.\n\nSkills Required:\n\n-Strong analytical and problem-solving skills. -Excellent communication, interpersonal, and collaboration skills. -Ability to translate complex technical information into easily understandable terms for non-technical audiences.\n\nSkills Preferred:\n\n-Java experience -SQL experience\n\nExperience Required:\n\n-ML experience and implementation experience\n\nExperience Preferred:\n\n-Experience with Agile methodologies is a plus. -Experience with vehicle configuration is a plus.\n",
  "enhancioed_versns": [],
  "selected_version": null,
  "feedback_history": [],
  "current_enhanced_version": null,
  "final_version": null,
  "actions": [
    {
      "action": "file_selected",
      "file_name": "DataAnalyticsAIMLJD (1).txt",
      "username": "Recruiter",
      "timestamp": "2025-03-20T10:17:14.160406"
    },
    {
      "action": "versions_generated",
      "version_count": 3,
      "username": "Recruiter",
      "timestamp": "2025-03-20T10:17:35.846499"
    }
  ],
  "enhanced_versions": [
    "Role Overview:\nThis role is a critical bridge between business operations and technical systems, blending strategic thinking, analytical prowess, and technical expertise. As a Configuration Specialist, you will play a pivotal role in ensuring our enterprise-level systems accurately reflect and support evolving business needs. By translating complex requirements into effective system configurations, you will drive efficiency, optimization, and continuous improvement across the organization.\n\nKey Responsibilities:\n- Collaborate closely with stakeholders from various departments to understand business requirements, document them thoroughly, and prioritize areas for system configuration updates\n- Translate business requirements into detailed technical configurations within our [mention specific system] backend, including developing and maintaining configuration specifications, creating and modifying data mappings and integrations, and implementing and testing new configurations\n- Analyze existing data to identify trends, inefficiencies, and opportunities for improvement, leveraging tools and techniques such as database querying, reporting, and data visualization\n- Proactively identify opportunities to streamline business processes and enhance system efficiency through configuration changes and the adoption of industry best practices\n- Rigorously test configurations to ensure they meet requirements and function as expected, participating actively in user acceptance testing (UAT)\n- Maintain comprehensive documentation of system configurations, processes, and troubleshooting steps to support ongoing operations and future enhancements\n- Work closely with developers, IT support, and other stakeholders to facilitate smooth implementation and provide ongoing support for system configurations\n\nRequired Skills:\n- Strong analytical and problem-solving skills, with the ability to break down complex challenges and devise effective solutions\n- Excellent communication, interpersonal, and collaboration skills, enabling you to translate technical information into easily understandable terms for non-technical audiences\n- Proficiency in data analysis, including the ability to query databases, generate reports, and utilize data visualization tools to uncover insights\n- Demonstrated experience in business process analysis and optimization, with a keen eye for identifying opportunities for improvement\n\nPreferred Skills:\n- Familiarity with Java and SQL, which are essential for working with our [mention specific system] backend\n- Experience in applying machine learning (ML) and artificial intelligence (AI) techniques to develop innovative solutions\n\nRequired Experience:\n- Minimum 3-5 years of experience in a configuration management, business analysis, or system administration role, with a track record of successfully translating business requirements into technical solutions\n- Proven experience in working with enterprise-level systems and managing complex configurations\n\nPreferred Experience:\n- Prior experience with Agile methodologies and working in a fast-paced, collaborative environment\n- Familiarity with the vehicle configuration domain, which would provide valuable context for this role\n\nTools & Technologies:\n- [Mention specific system] platform\n- SQL and data analysis tools\n- Collaboration and documentation tools (e.g., Jira, Confluence)\n\nWork Environment & Expectations:\n- This role will involve a mix of collaborative work with cross-functional teams and independent research and analysis\n- You will be expected to work closely with stakeholders to understand their needs, champion configuration changes, and drive continuous improvement\n- The ability to work in an Agile environment, adapt to changing priorities, and deliver high-quality work under tight deadlines is essential",
    "Role Overview:\nAs a Configuration Specialist, you will play a pivotal role in bridging the gap between our business operations and the underlying technical systems that support them. By deeply understanding the complexities of our [mention specific system] platform and translating business requirements into effective configurations, you will drive efficiency, optimization, and continuous improvement across the organization. This role requires a unique blend of strategic thinking, analytical prowess, and technical expertise, making it a crucial contributor to the success of our enterprise.\n\nKey Responsibilities:\n- Engage with stakeholders from various departments to thoroughly understand their business needs, document detailed requirements, and prioritize areas for system configuration updates\n- Leverage your technical expertise to configure and maintain our [mention specific system] backend, including developing and modifying data mappings, integrations, and other core components\n- Analyze existing data and processes to identify opportunities for improvement, utilizing tools and techniques such as database querying, reporting, and data visualization to uncover insights\n- Proactively propose and implement configuration changes that streamline business operations, enhance system efficiency, and align with industry best practices\n- Rigorously test configurations to ensure they meet requirements and function as expected, actively participating in user acceptance testing (UAT) and providing feedback to refine the solutions\n- Maintain comprehensive documentation of system configurations, processes, and troubleshooting steps to support ongoing operations and enable future enhancements\n- Collaborate closely with developers, IT support, and other stakeholders to facilitate smooth implementation and provide ongoing support for the system configurations you manage\n\nRequired Skills:\n- Exceptional analytical and problem-solving skills, with the ability to break down complex challenges and devise effective, data-driven solutions\n- Strong communication, interpersonal, and collaboration abilities, enabling you to translate technical information into easily understandable terms for non-technical audiences\n- Proficiency in data analysis, including the ability to query databases, generate reports, and leverage data visualization tools to uncover insights and support decision-making\n- Demonstrated experience in business process analysis and optimization, with a keen eye for identifying opportunities for improvement and driving change\n\nPreferred Skills:\n- Familiarity with Java and SQL, which are essential for working with our [mention specific system] backend\n- Experience in applying machine learning (ML) and artificial intelligence (AI) techniques to develop innovative solutions and drive continuous improvement\n\nRequired Experience:\n- Minimum 3-5 years of experience in a configuration management, business analysis, or system administration role, with a proven track record of successfully translating business requirements into technical solutions\n- Extensive experience working with enterprise-level systems and managing complex configurations\n\nPreferred Experience:\n- Prior experience working in an Agile environment and collaborating effectively with cross-functional teams\n- Familiarity with the vehicle configuration domain, which would provide valuable context and domain-specific knowledge for this role\n\nTools & Technologies:\n- [Mention specific system] platform\n- SQL and data analysis tools\n- Collaboration and documentation tools (e.g., Jira, Confluence)\n\nWork Environment & Expectations:\n- This role will involve a balanced mix of collaborative work with stakeholders and independent research and analysis\n- You will be expected to act as a strategic partner, working closely with business leaders to understand their evolving needs and champion configuration changes that drive operational excellence\n- The ability to work in a fast-paced, Agile environment, adapt to changing priorities, and deliver high-quality work under tight deadlines is essential",
    "Role Overview:\nAs a Configuration Specialist, you will be a vital link between our business operations and the technical systems that power them. With your deep understanding of our [mention specific system] platform and your ability to translate complex requirements into effective configurations, you will play a pivotal role in driving efficiency, optimization, and continuous improvement across the organization. This role requires a unique blend of analytical thinking, technical expertise, and strategic problem-solving, making it a critical contributor to the overall success of our enterprise.\n\nKey Responsibilities:\n- Partner closely with stakeholders from various departments to thoroughly understand their business needs, document detailed requirements, and prioritize areas for system configuration updates\n- Leverage your technical proficiency to configure and maintain the backend of our [mention specific system], including developing and modifying data mappings, integrations, and other core components\n- Analyze existing data and processes to identify opportunities for improvement, utilizing tools and techniques such as database querying, reporting, and data visualization to uncover valuable insights\n- Proactively propose and implement configuration changes that streamline business operations, enhance system efficiency, and align with industry best practices\n- Rigorously test configurations to ensure they meet requirements and function as expected, actively participating in user acceptance testing (UAT) and providing feedback to refine the solutions\n- Maintain comprehensive documentation of system configurations, processes, and troubleshooting steps to support ongoing operations and enable future enhancements\n- Collaborate closely with developers, IT support, and other stakeholders to facilitate smooth implementation and provide ongoing support for the system configurations you manage\n\nRequired Skills:\n- Exceptional analytical and problem-solving skills, with the ability to break down complex challenges, analyze data, and devise effective, data-driven solutions\n- Excellent communication, interpersonal, and collaboration abilities, enabling you to translate technical information into easily understandable terms for non-technical audiences\n- Proficiency in data analysis, including the ability to query databases, generate reports, and leverage data visualization tools to uncover insights and support decision-making\n- Demonstrated experience in business process analysis and optimization, with a keen eye for identifying opportunities for improvement and driving change\n\nPreferred Skills:\n- Familiarity with Java and SQL, which are essential for working with our [mention specific system] backend\n- Experience in applying machine learning (ML) and artificial intelligence (AI) techniques to develop innovative solutions and drive continuous improvement\n\nRequired Experience:\n- Minimum 3-5 years of experience in a configuration management, business analysis, or system administration role, with a proven track record of successfully translating business requirements into technical solutions\n- Extensive experience working with enterprise-level systems and managing complex configurations\n\nPreferred Experience:\n- Prior experience in an Agile environment, collaborating effectively with cross-functional teams to deliver high-quality solutions\n- Familiarity with the vehicle configuration domain, which would provide valuable context and domain-specific knowledge for this role\n\nTools & Technologies:\n- [Mention specific system] platform\n- SQL and data analysis tools\n- Collaboration and documentation tools (e.g., Jira, Confluence)\n\nWork Environment & Expectations:\n- This role will involve a balanced mix of collaborative work with stakeholders and independent research and analysis\n- You will be expected to act as a strategic partner, working closely with business leaders to understand their evolving needs and champion configuration changes that drive operational excellence\n- The ability to work in a fast-paced, Agile environment, adapt to changing priorities, and deliver high-quality work under tight deadlines is essential"
  ]
}